README.md
setup.py
aiacc_nccl_plugin/__init__.py
aiacc_nccl_plugin/libnccl-net.so.0.0.0
aiacc_nccl_plugin.egg-info/PKG-INFO
aiacc_nccl_plugin.egg-info/SOURCES.txt
aiacc_nccl_plugin.egg-info/dependency_links.txt
aiacc_nccl_plugin.egg-info/requires.txt
aiacc_nccl_plugin.egg-info/top_level.txt