Metadata-Version: 2.1
Name: aiacc-nccl-plugin
Version: 2.0.1
Summary: AIACC-NCCL is an AI-Accelerator communication framework for NVIDIA-NCCL. It implements optimized all-reduce, all-gather, reduce, broadcast, reduce-scatter, all-to-all,as well as any send/receive based communication pattern.It has been optimized to achieve high bandwidth on aliyun machines using PCIe, NVLink, NVswitch,as well as networking using InfiniBand Verbs, eRDMA or TCP/IP sockets.
Home-page: https://help.aliyun.com/document_detail/462422.html?spm=a2c4g.462031.0.0.c5f96b4drcx52F
Author: Alibaba Cloud
Author-email: ziqi.yzq@alibaba-inc.com
License: Copyright (C) Alibaba Group Holding Limited
Keywords: Distributed,Deep Learning,Communication,NCCL,AIACC
Platform: UNKNOWN
Requires-Python: >=3.0
